one_gadget/__init__.py
one_gadget-1.1.0.dist-info/METADATA
one_gadget-1.1.0.dist-info/RECORD
one_gadget-1.1.0.dist-info/WHEEL
one_gadget-1.1.0.dist-info/top_level.txt
