Metadata-Version: 2.1
Name: one-gadget
Version: 1.1.0
Summary: A python library to find one-gadget
Home-page: https://github.com/szk3y/one-gadget-lib
Author: szk3y
Author-email: d4tt423@gmail.com
License: UNKNOWN
Platform: UNKNOWN
Classifier: Programming Language :: Python :: 2
Classifier: Programming Language :: Python :: 3
Classifier: License :: OSI Approved :: MIT License
Classifier: Operating System :: OS Independent
Requires-Dist: capstone
Requires-Dist: pyelftools
